{
    "input1.in": {
        "Máx Iterações - 10": {
            "Janela - 2": 31621,
            "Janela - 3": 31621,
            "Janela - 4": 31621,
            "Janela - 5": 30548,
            "Janela - 6": 31621,
            "Janela - 7": 31621,
            "Janela - 8": 31621,
            "Janela - 9": 30548
        },
        "Máx Iterações - 100": {
            "Janela - 2": 31621,
            "Janela - 3": 31621,
            "Janela - 4": 31621,
            "Janela - 5": 31621,
            "Janela - 6": 31621,
            "Janela - 7": 31621,
            "Janela - 8": 31621,
            "Janela - 9": 31621
        },
        "Máx Iterações - 1000": {
            "Janela - 2": 31621,
            "Janela - 3": 31621,
            "Janela - 4": 31621,
            "Janela - 5": 31621,
            "Janela - 6": 31621,
            "Janela - 7": 31621,
            "Janela - 8": 31621,
            "Janela - 9": 31621
        },
        "Máx Iterações - 10000": {
            "Janela - 2": 31621,
            "Janela - 3": 31621,
            "Janela - 4": 31621,
            "Janela - 5": 31621,
            "Janela - 6": 31621,
            "Janela - 7": 31621,
            "Janela - 8": 31621,
            "Janela - 9": 31621
        }
    },
    "input2.in": {
        "Máx Iterações - 10": {
            "Janela - 2": 67829,
            "Janela - 3": 67829,
            "Janela - 4": 67829,
            "Janela - 5": 67829,
            "Janela - 6": 67829,
            "Janela - 7": 64593,
            "Janela - 8": 67829,
            "Janela - 9": 67829
        },
        "Máx Iterações - 100": {
            "Janela - 2": 67829,
            "Janela - 3": 67829,
            "Janela - 4": 67829,
            "Janela - 5": 67829,
            "Janela - 6": 67829,
            "Janela - 7": 67829,
            "Janela - 8": 67829,
            "Janela - 9": 67829
        },
        "Máx Iterações - 1000": {
            "Janela - 2": 67829,
            "Janela - 3": 67829,
            "Janela - 4": 67829,
            "Janela - 5": 67829,
            "Janela - 6": 67829,
            "Janela - 7": 67829,
            "Janela - 8": 67829,
            "Janela - 9": 67829
        },
        "Máx Iterações - 10000": {
            "Janela - 2": 67829,
            "Janela - 3": 67829,
            "Janela - 4": 67829,
            "Janela - 5": 67829,
            "Janela - 6": 67829,
            "Janela - 7": 67829,
            "Janela - 8": 67829,
            "Janela - 9": 67829
        }
    },
    "input3.in": {
        "Máx Iterações - 10": {
            "Janela - 2": 143449,
            "Janela - 3": 143449,
            "Janela - 4": 143449,
            "Janela - 5": 143449,
            "Janela - 6": 143449,
            "Janela - 7": 143449,
            "Janela - 8": 143449,
            "Janela - 9": 143449
        },
        "Máx Iterações - 100": {
            "Janela - 2": 143449,
            "Janela - 3": 143449,
            "Janela - 4": 143449,
            "Janela - 5": 143449,
            "Janela - 6": 143449,
            "Janela - 7": 143449,
            "Janela - 8": 143449,
            "Janela - 9": 143449
        },
        "Máx Iterações - 1000": {
            "Janela - 2": 143449,
            "Janela - 3": 143449,
            "Janela - 4": 143449,
            "Janela - 5": 143449,
            "Janela - 6": 143449,
            "Janela - 7": 143449,
            "Janela - 8": 143449,
            "Janela - 9": 143449
        },
        "Máx Iterações - 10000": {
            "Janela - 2": 143449,
            "Janela - 3": 143449,
            "Janela - 4": 143449,
            "Janela - 5": 143449,
            "Janela - 6": 143449,
            "Janela - 7": 143449,
            "Janela - 8": 143449,
            "Janela - 9": 143449
        }
    },
    "input4.in": {
        "Máx Iterações - 10": {
            "Janela - 2": 28840,
            "Janela - 3": 28840,
            "Janela - 4": 28840,
            "Janela - 5": 28840,
            "Janela - 6": 28840,
            "Janela - 7": 28840,
            "Janela - 8": 28840,
            "Janela - 9": 28840
        },
        "Máx Iterações - 100": {
            "Janela - 2": 28840,
            "Janela - 3": 28840,
            "Janela - 4": 28840,
            "Janela - 5": 28840,
            "Janela - 6": 28840,
            "Janela - 7": 28840,
            "Janela - 8": 28840,
            "Janela - 9": 28840
        },
        "Máx Iterações - 1000": {
            "Janela - 2": 28840,
            "Janela - 3": 28840,
            "Janela - 4": 28840,
            "Janela - 5": 28840,
            "Janela - 6": 28840,
            "Janela - 7": 28840,
            "Janela - 8": 28840,
            "Janela - 9": 28840
        },
        "Máx Iterações - 10000": {
            "Janela - 2": 28840,
            "Janela - 3": 28840,
            "Janela - 4": 28840,
            "Janela - 5": 28840,
            "Janela - 6": 28840,
            "Janela - 7": 28840,
            "Janela - 8": 28840,
            "Janela - 9": 28840
        }
    },
    "input5.in": {
        "Máx Iterações - 10": {
            "Janela - 2": 15785,
            "Janela - 3": 15785,
            "Janela - 4": 15785,
            "Janela - 5": 15785,
            "Janela - 6": 15785,
            "Janela - 7": 15785,
            "Janela - 8": 15785,
            "Janela - 9": 15785
        },
        "Máx Iterações - 100": {
            "Janela - 2": 15785,
            "Janela - 3": 15785,
            "Janela - 4": 15785,
            "Janela - 5": 15785,
            "Janela - 6": 15785,
            "Janela - 7": 15785,
            "Janela - 8": 15785,
            "Janela - 9": 15785
        },
        "Máx Iterações - 1000": {
            "Janela - 2": 15785,
            "Janela - 3": 15785,
            "Janela - 4": 15785,
            "Janela - 5": 15785,
            "Janela - 6": 15785,
            "Janela - 7": 15785,
            "Janela - 8": 15785,
            "Janela - 9": 15785
        },
        "Máx Iterações - 10000": {
            "Janela - 2": 15785,
            "Janela - 3": 15785,
            "Janela - 4": 15785,
            "Janela - 5": 15785,
            "Janela - 6": 15785,
            "Janela - 7": 15785,
            "Janela - 8": 15785,
            "Janela - 9": 15785
        }
    },
    "input6.in": {
        "Máx Iterações - 10": {
            "Janela - 2": 99861,
            "Janela - 3": 99861,
            "Janela - 4": 99861,
            "Janela - 5": 99861,
            "Janela - 6": 99861,
            "Janela - 7": 99861,
            "Janela - 8": 99861,
            "Janela - 9": 99861
        },
        "Máx Iterações - 100": {
            "Janela - 2": 99861,
            "Janela - 3": 99861,
            "Janela - 4": 99861,
            "Janela - 5": 99861,
            "Janela - 6": 99861,
            "Janela - 7": 99861,
            "Janela - 8": 99861,
            "Janela - 9": 99861
        },
        "Máx Iterações - 1000": {
            "Janela - 2": 99861,
            "Janela - 3": 99861,
            "Janela - 4": 99861,
            "Janela - 5": 99861,
            "Janela - 6": 99861,
            "Janela - 7": 99861,
            "Janela - 8": 99861,
            "Janela - 9": 99861
        },
        "Máx Iterações - 10000": {
            "Janela - 2": 99861,
            "Janela - 3": 99861,
            "Janela - 4": 99861,
            "Janela - 5": 99861,
            "Janela - 6": 99861,
            "Janela - 7": 99861,
            "Janela - 8": 99861,
            "Janela - 9": 99861
        }
    },
    "input7.in": {
        "Máx Iterações - 10": {
            "Janela - 2": 1922,
            "Janela - 3": 1940,
            "Janela - 4": 1922,
            "Janela - 5": 1922,
            "Janela - 6": 1903,
            "Janela - 7": 1901,
            "Janela - 8": 1916,
            "Janela - 9": 1922
        },
        "Máx Iterações - 100": {
            "Janela - 2": 1922,
            "Janela - 3": 1940,
            "Janela - 4": 1940,
            "Janela - 5": 1940,
            "Janela - 6": 1922,
            "Janela - 7": 1922,
            "Janela - 8": 1940,
            "Janela - 9": 1922
        },
        "Máx Iterações - 1000": {
            "Janela - 2": 1922,
            "Janela - 3": 1940,
            "Janela - 4": 1940,
            "Janela - 5": 1940,
            "Janela - 6": 1940,
            "Janela - 7": 1940,
            "Janela - 8": 1940,
            "Janela - 9": 1940
        },
        "Máx Iterações - 10000": {
            "Janela - 2": 1922,
            "Janela - 3": 1940,
            "Janela - 4": 1940,
            "Janela - 5": 1940,
            "Janela - 6": 1940,
            "Janela - 7": 1940,
            "Janela - 8": 1940,
            "Janela - 9": 1940
        }
    },
    "input8.in": {
        "Máx Iterações - 10": {
            "Janela - 2": 489,
            "Janela - 3": 497,
            "Janela - 4": 741,
            "Janela - 5": 738,
            "Janela - 6": 741,
            "Janela - 7": 741,
            "Janela - 8": 741,
            "Janela - 9": 737
        },
        "Máx Iterações - 100": {
            "Janela - 2": 491,
            "Janela - 3": 733,
            "Janela - 4": 738,
            "Janela - 5": 741,
            "Janela - 6": 741,
            "Janela - 7": 741,
            "Janela - 8": 741,
            "Janela - 9": 741
        },
        "Máx Iterações - 1000": {
            "Janela - 2": 496,
            "Janela - 3": 735,
            "Janela - 4": 741,
            "Janela - 5": 741,
            "Janela - 6": 741,
            "Janela - 7": 741,
            "Janela - 8": 741,
            "Janela - 9": 741
        },
        "Máx Iterações - 10000": {
            "Janela - 2": 737,
            "Janela - 3": 741,
            "Janela - 4": 741,
            "Janela - 5": 741,
            "Janela - 6": 741,
            "Janela - 7": 741,
            "Janela - 8": 741,
            "Janela - 9": 741
        }
    },
    "input9.in": {
        "Máx Iterações - 10": {
            "Janela - 2": 9627,
            "Janela - 3": 9685,
            "Janela - 4": 9756,
            "Janela - 5": 9771,
            "Janela - 6": 9812,
            "Janela - 7": 9866,
            "Janela - 8": 10254,
            "Janela - 9": 10218
        },
        "Máx Iterações - 100": {
            "Janela - 2": 9674,
            "Janela - 3": 9914,
            "Janela - 4": 10110,
            "Janela - 5": 10257,
            "Janela - 6": 10275,
            "Janela - 7": 10271,
            "Janela - 8": 10271,
            "Janela - 9": 10277
        },
        "Máx Iterações - 1000": {
            "Janela - 2": 9916,
            "Janela - 3": 10193,
            "Janela - 4": 10279,
            "Janela - 5": 10275,
            "Janela - 6": 10277,
            "Janela - 7": 10281,
            "Janela - 8": 10280,
            "Janela - 9": 10281
        },
        "Máx Iterações - 10000": {
            "Janela - 2": 9908,
            "Janela - 3": 10196,
            "Janela - 4": 10279,
            "Janela - 5": 10281,
            "Janela - 6": 10281,
            "Janela - 7": 10281,
            "Janela - 8": 10281,
            "Janela - 9": 10281
        }
    },
    "input10.in": {
        "Máx Iterações - 10": {
            "Janela - 2": 19333,
            "Janela - 3": 19718,
            "Janela - 4": 19639,
            "Janela - 5": 20085,
            "Janela - 6": 20094,
            "Janela - 7": 19937,
            "Janela - 8": 19902,
            "Janela - 9": 20031
        },
        "Máx Iterações - 100": {
            "Janela - 2": 19333,
            "Janela - 3": 20095,
            "Janela - 4": 20097,
            "Janela - 5": 20125,
            "Janela - 6": 20136,
            "Janela - 7": 20113,
            "Janela - 8": 20149,
            "Janela - 9": 20149
        },
        "Máx Iterações - 1000": {
            "Janela - 2": 19368,
            "Janela - 3": 20095,
            "Janela - 4": 20125,
            "Janela - 5": 20149,
            "Janela - 6": 20149,
            "Janela - 7": 20149,
            "Janela - 8": 20149,
            "Janela - 9": 20149
        },
        "Máx Iterações - 10000": {
            "Janela - 2": 20046,
            "Janela - 3": 20095,
            "Janela - 4": 20149,
            "Janela - 5": 20149,
            "Janela - 6": 20149,
            "Janela - 7": 20149,
            "Janela - 8": 20149,
            "Janela - 9": 20149
        }
    },
    "input11.in": {
        "Máx Iterações - 10": {
            "Janela - 2": 29965,
            "Janela - 3": 29972,
            "Janela - 4": 29990,
            "Janela - 5": 29990,
            "Janela - 6": 29990,
            "Janela - 7": 29990,
            "Janela - 8": 29965,
            "Janela - 9": 29998
        },
        "Máx Iterações - 100": {
            "Janela - 2": 29965,
            "Janela - 3": 29972,
            "Janela - 4": 29990,
            "Janela - 5": 29990,
            "Janela - 6": 29990,
            "Janela - 7": 30000,
            "Janela - 8": 29998,
            "Janela - 9": 29998
        },
        "Máx Iterações - 1000": {
            "Janela - 2": 29965,
            "Janela - 3": 29972,
            "Janela - 4": 29990,
            "Janela - 5": 29990,
            "Janela - 6": 29990,
            "Janela - 7": 30000,
            "Janela - 8": 30000,
            "Janela - 9": 30000
        },
        "Máx Iterações - 10000": {
            "Janela - 2": 29965,
            "Janela - 3": 29972,
            "Janela - 4": 29990,
            "Janela - 5": 29990,
            "Janela - 6": 29990,
            "Janela - 7": 30000,
            "Janela - 8": 30000,
            "Janela - 9": 30000
        }
    },
    "input12.in": {
        "Máx Iterações - 10": {
            "Janela - 2": 49885,
            "Janela - 3": 49885,
            "Janela - 4": 49885,
            "Janela - 5": 49885,
            "Janela - 6": 49885,
            "Janela - 7": 49885,
            "Janela - 8": 49885,
            "Janela - 9": 49885
        },
        "Máx Iterações - 100": {
            "Janela - 2": 49885,
            "Janela - 3": 49885,
            "Janela - 4": 49885,
            "Janela - 5": 49885,
            "Janela - 6": 49885,
            "Janela - 7": 49885,
            "Janela - 8": 49885,
            "Janela - 9": 49885
        },
        "Máx Iterações - 1000": {
            "Janela - 2": 49885,
            "Janela - 3": 49885,
            "Janela - 4": 49885,
            "Janela - 5": 49885,
            "Janela - 6": 49885,
            "Janela - 7": 49885,
            "Janela - 8": 49885,
            "Janela - 9": 49885
        },
        "Máx Iterações - 10000": {
            "Janela - 2": 49885,
            "Janela - 3": 49885,
            "Janela - 4": 49885,
            "Janela - 5": 49885,
            "Janela - 6": 49885,
            "Janela - 7": 49885,
            "Janela - 8": 49885,
            "Janela - 9": 49885
        }
    },
    "input13.in": {
        "Máx Iterações - 10": {
            "Janela - 2": 49395,
            "Janela - 3": 49398,
            "Janela - 4": 49398,
            "Janela - 5": 49398,
            "Janela - 6": 49398,
            "Janela - 7": 49398,
            "Janela - 8": 49398,
            "Janela - 9": 49398
        },
        "Máx Iterações - 100": {
            "Janela - 2": 49398,
            "Janela - 3": 49398,
            "Janela - 4": 49398,
            "Janela - 5": 49398,
            "Janela - 6": 49398,
            "Janela - 7": 49398,
            "Janela - 8": 49398,
            "Janela - 9": 49398
        },
        "Máx Iterações - 1000": {
            "Janela - 2": 49398,
            "Janela - 3": 49398,
            "Janela - 4": 49398,
            "Janela - 5": 49398,
            "Janela - 6": 49398,
            "Janela - 7": 49398,
            "Janela - 8": 49398,
            "Janela - 9": 49398
        },
        "Máx Iterações - 10000": {
            "Janela - 2": 49398,
            "Janela - 3": 49398,
            "Janela - 4": 49398,
            "Janela - 5": 49398,
            "Janela - 6": 49398,
            "Janela - 7": 49398,
            "Janela - 8": 49398,
            "Janela - 9": 49398
        }
    },
    "input14.in": {
        "Máx Iterações - 10": {
            "Janela - 2": 20880,
            "Janela - 3": 20880,
            "Janela - 4": 20880,
            "Janela - 5": 20880,
            "Janela - 6": 20880,
            "Janela - 7": 20880,
            "Janela - 8": 20880,
            "Janela - 9": 20880
        },
        "Máx Iterações - 100": {
            "Janela - 2": 20880,
            "Janela - 3": 20880,
            "Janela - 4": 20880,
            "Janela - 5": 20880,
            "Janela - 6": 20880,
            "Janela - 7": 20880,
            "Janela - 8": 20880,
            "Janela - 9": 20880
        },
        "Máx Iterações - 1000": {
            "Janela - 2": 20880,
            "Janela - 3": 20880,
            "Janela - 4": 20880,
            "Janela - 5": 20880,
            "Janela - 6": 20880,
            "Janela - 7": 20880,
            "Janela - 8": 20880,
            "Janela - 9": 20880
        },
        "Máx Iterações - 10000": {
            "Janela - 2": 20880,
            "Janela - 3": 20880,
            "Janela - 4": 20880,
            "Janela - 5": 20880,
            "Janela - 6": 20880,
            "Janela - 7": 20880,
            "Janela - 8": 20880,
            "Janela - 9": 20880
        }
    },
    "input15.in": {
        "Máx Iterações - 10": {
            "Janela - 2": 20676,
            "Janela - 3": 20676,
            "Janela - 4": 20676,
            "Janela - 5": 20676,
            "Janela - 6": 20676,
            "Janela - 7": 20676,
            "Janela - 8": 396,
            "Janela - 9": 20676
        },
        "Máx Iterações - 100": {
            "Janela - 2": 20676,
            "Janela - 3": 20676,
            "Janela - 4": 20676,
            "Janela - 5": 20676,
            "Janela - 6": 20676,
            "Janela - 7": 20676,
            "Janela - 8": 20676,
            "Janela - 9": 20676
        },
        "Máx Iterações - 1000": {
            "Janela - 2": 20676,
            "Janela - 3": 20676,
            "Janela - 4": 20676,
            "Janela - 5": 20676,
            "Janela - 6": 20676,
            "Janela - 7": 20676,
            "Janela - 8": 20676,
            "Janela - 9": 20676
        },
        "Máx Iterações - 10000": {
            "Janela - 2": 20676,
            "Janela - 3": 20676,
            "Janela - 4": 20676,
            "Janela - 5": 20676,
            "Janela - 6": 20676,
            "Janela - 7": 20676,
            "Janela - 8": 20676,
            "Janela - 9": 20676
        }
    },
    "input16.in": {
        "Máx Iterações - 10": {
            "Janela - 2": 1997,
            "Janela - 3": 2001,
            "Janela - 4": 2001,
            "Janela - 5": 46084,
            "Janela - 6": 46084,
            "Janela - 7": 45717,
            "Janela - 8": 46118,
            "Janela - 9": 2001
        },
        "Máx Iterações - 100": {
            "Janela - 2": 1997,
            "Janela - 3": 46044,
            "Janela - 4": 46118,
            "Janela - 5": 46044,
            "Janela - 6": 46084,
            "Janela - 7": 46084,
            "Janela - 8": 45927,
            "Janela - 9": 45717
        },
        "Máx Iterações - 1000": {
            "Janela - 2": 45927,
            "Janela - 3": 46057,
            "Janela - 4": 46118,
            "Janela - 5": 46118,
            "Janela - 6": 46118,
            "Janela - 7": 46118,
            "Janela - 8": 46044,
            "Janela - 9": 46118
        },
        "Máx Iterações - 10000": {
            "Janela - 2": 45927,
            "Janela - 3": 46118,
            "Janela - 4": 46118,
            "Janela - 5": 46118,
            "Janela - 6": 46118,
            "Janela - 7": 46121,
            "Janela - 8": 46121,
            "Janela - 9": 46121
        }
    }
}